bbrl_gym/__init__.py
bbrl_gym/_version.py
bbrl_gym/envs/__init__.py
bbrl_gym/envs/continuous_2D_mdp.py
bbrl_gym/envs/continuous_cartpole.py
bbrl_gym/envs/continuous_line_mdp.py
bbrl_gym/envs/debug_env.py
bbrl_gym/envs/line_mdp.py
bbrl_gym/envs/maze_mdp.py
bbrl_gym/envs/rocket_lander.py
my_gym/__init__.py
my_gym/envs/__init__.py
my_gym/envs/continuous_2D_mdp.py
my_gym/envs/continuous_cartpole.py
my_gym/envs/continuous_line_mdp.py
my_gym/envs/debug_env.py
my_gym/envs/line_mdp.py
my_gym/envs/maze_mdp.py
my_gym/envs/rocket_lander.py
bbrl_gym-1.2.5.dist-info/LICENSE
bbrl_gym-1.2.5.dist-info/METADATA
bbrl_gym-1.2.5.dist-info/WHEEL
bbrl_gym-1.2.5.dist-info/top_level.txt
bbrl_gym-1.2.5.dist-info/RECORD
